[
  {"itemCode": "3684480", "item1": "05 M PB14 TAPE NAT", "area": "111", "plans": {"Apr": 0, "May": 0, "Jun": 0, "Jul": 0, "Aug": 0, "Sep": 0, "Oct": 0, "Nov": 0, "Dec": 0, "Jan": 0, "Feb": 0, "Mar": 0}},
  {"itemCode": "3599630", "item1": "03 C PB12 TAPE NAT", "area": "111", "plans": {"Apr": 0, "May": 0, "Jun": 0, "Jul": 0, "Aug": 0, "Sep": 0, "Oct": 0, "Nov": 0, "Dec": 0, "Jan": 0, "Feb": 0, "Mar": 0}},
  {"itemCode": "3603610", "item1": "05 CI PB16 TAPE NAT", "area": "111", "plans": {"Apr": 0, "May": 0, "Jun": 0, "Jul": 0, "Aug": 0, "Sep": 0, "Oct": 0, "Nov": 0, "Dec": 0, "Jan": 0, "Feb": 0, "Mar": 0}},
  {"itemCode": "6799450", "item1": "03 VS PB12 TAPE NAT", "area": "111", "plans": {"Apr": 0, "May": 0, "Jun": 0, "Jul": 0, "Aug": 0, "Sep": 0, "Oct": 0, "Nov": 0, "Dec": 0, "Jan": 0, "Feb": 0, "Mar": 0}},
  {"itemCode": "3638190", "item1": "05 VS PB14 TAPE NAT", "area": "111", "plans": {"Apr": 0, "May": 0, "Jun": 0, "Jul": 0, "Aug": 0, "Sep": 0, "Oct": 0, "Nov": 0, "Dec": 0, "Jan": 0, "Feb": 0, "Mar": 0}},
  {"itemCode": "6385220", "item1": "08 VS PB16 TAPE NAT INA-2", "area": "111", "plans": {"Apr": 0, "May": 0, "Jun": 0, "Jul": 0, "Aug": 0, "Sep": 0, "Oct": 0, "Nov": 0, "Dec": 0, "Jan": 0, "Feb": 0, "Mar": 0}},
  {"itemCode": "3651560", "item1": "03 Y PB12 TAPE NAT", "area": "111", "plans": {"Apr": 0, "May": 0, "Jun": 0, "Jul": 0, "Aug": 0, "Sep": 0, "Oct": 0, "Nov": 0, "Dec": 0, "Jan": 0, "Feb": 0, "Mar": 0}},
  {"itemCode": "6859440", "item1": "05 CI R16S1 TAPE NAT", "area": "111", "plans": {"Apr": 0, "May": 0, "Jun": 0, "Jul": 0, "Aug": 0, "Sep": 0, "Oct": 0, "Nov": 0, "Dec": 0, "Jan": 0, "Feb": 0, "Mar": 0}},
  {"itemCode": "3707960", "item1": "45 CF PB14 TAPE NAT", "area": "111", "plans": {"Apr": 0, "May": 0, "Jun": 0, "Jul": 0, "Aug": 0, "Sep": 0, "Oct": 0, "Nov": 0, "Dec": 0, "Jan": 0, "Feb": 0, "Mar": 0}},
  {"itemCode": "3980180", "item1": "04 Y PB14 TAPE NAT", "area": "111", "plans": {"Apr": 0, "May": 0, "Jun": 0, "Jul": 0, "Aug": 0, "Sep": 0, "Oct": 0, "Nov": 0, "Dec": 0, "Jan": 0, "Feb": 0, "Mar": 0}},
  {"itemCode": "6859430", "item1": "03 C R12S1 TAPE NAT", "area": "111", "plans": {"Apr": 0, "May": 0, "Jun": 0, "Jul": 0, "Aug": 0, "Sep": 0, "Oct": 0, "Nov": 0, "Dec": 0, "Jan": 0, "Feb": 0, "Mar": 0}},
  {"itemCode": "8914990", "item1": "03 CF PBB18 TAPE NAT", "area": "111", "plans": {"Apr": 0, "May": 0, "Jun": 0, "Jul": 0, "Aug": 0, "Sep": 0, "Oct": 0, "Nov": 0, "Dec": 0, "Jan": 0, "Feb": 0, "Mar": 0}},
  {"itemCode": "6699580", "item1": "03 VS PBG12 TAPE NAT", "area": "111", "plans": {"Apr": 0, "May": 0, "Jun": 0, "Jul": 0, "Aug": 0, "Sep": 0, "Oct": 0, "Nov": 0, "Dec": 0, "Jan": 0, "Feb": 0, "Mar": 0}},
  {"itemCode": "8721450", "item1": "05 VS PBB18 TAPE NAT", "area": "111", "plans": {"Apr": 0, "May": 0, "Jun": 0, "Jul": 0, "Aug": 0, "Sep": 0, "Oct": 0, "Nov": 0, "Dec": 0, "Jan": 0, "Feb": 0, "Mar": 0}},
  {"itemCode": "6699590", "item1": "05 VS PBG14 TAPE NAT", "area": "111", "plans": {"Apr": 0, "May": 0, "Jun": 0, "Jul": 0, "Aug": 0, "Sep": 0, "Oct": 0, "Nov": 0, "Dec": 0, "Jan": 0, "Feb": 0, "Mar": 0}},
  {"itemCode": "8469200", "item1": "03 VS PBB18 TAPE NAT", "area": "111", "plans": {"Apr": 0, "May": 0, "Jun": 0, "Jul": 0, "Aug": 0, "Sep": 0, "Oct": 0, "Nov": 0, "Dec": 0, "Jan": 0, "Feb": 0, "Mar": 0}},
  {"itemCode": "6653940", "item1": "03 Y R12S1 TAPE DOPE NAT", "area": "111", "plans": {"Apr": 0, "May": 0, "Jun": 0, "Jul": 0, "Aug": 0, "Sep": 0, "Oct": 0, "Nov": 0, "Dec": 0, "Jan": 0, "Feb": 0, "Mar": 0}},
  {"itemCode": "3852210", "item1": "03 C P12S1 TAPE DOPE NAT", "area": "111", "plans": {"Apr": 0, "May": 0, "Jun": 0, "Jul": 0, "Aug": 0, "Sep": 0, "Oct": 0, "Nov": 0, "Dec": 0, "Jan": 0, "Feb": 0, "Mar": 0}},
  {"itemCode": "9286", "item1": "05 YK2 CORD", "area": "121", "plans": {"Apr": 0, "May": 0, "Jun": 0, "Jul": 0, "Aug": 0, "Sep": 0, "Oct": 0, "Nov": 0, "Dec": 0, "Jan": 0, "Feb": 0, "Mar": 0}},
  {"itemCode": "1007230", "item1": "05 VK8 CORD", "area": "121", "plans": {"Apr": 0, "May": 0, "Jun": 0, "Jul": 0, "Aug": 0, "Sep": 0, "Oct": 0, "Nov": 0, "Dec": 0, "Jan": 0, "Feb": 0, "Mar": 0}},
  {"itemCode": "13852", "item1": "03 K2 CORD", "area": "121", "plans": {"Apr": 0, "May": 0, "Jun": 0, "Jul": 0, "Aug": 0, "Sep": 0, "Oct": 0, "Nov": 0, "Dec": 0, "Jan": 0, "Feb": 0, "Mar": 0}},
  {"itemCode": "1136450", "item1": "08 VK3 CORD", "area": "121", "plans": {"Apr": 0, "May": 0, "Jun": 0, "Jul": 0, "Aug": 0, "Sep": 0, "Oct": 0, "Nov": 0, "Dec": 0, "Jan": 0, "Feb": 0, "Mar": 0}},
  {"itemCode": "6723350", "item1": "03 VK9 CORD", "area": "121", "plans": {"Apr": 0, "May": 0, "Jun": 0, "Jul": 0, "Aug": 0, "Sep": 0, "Oct": 0, "Nov": 0, "Dec": 0, "Jan": 0, "Feb": 0, "Mar": 0}},
  {"itemCode": "6127230", "item1": "04 YK1 CORD HUALON", "area": "121", "plans": {"Apr": 0, "May": 0, "Jun": 0, "Jul": 0, "Aug": 0, "Sep": 0, "Oct": 0, "Nov": 0, "Dec": 0, "Jan": 0, "Feb": 0, "Mar": 0}},
  {"itemCode": "6653680", "item1": "03 K2RD CORD", "area": "121", "plans": {"Apr": 0, "May": 0, "Jun": 0, "Jul": 0, "Aug": 0, "Sep": 0, "Oct": 0, "Nov": 0, "Dec": 0, "Jan": 0, "Feb": 0, "Mar": 0}},
  {"itemCode": "2734780", "item1": "05 VKG CORD", "area": "121", "plans": {"Apr": 0, "May": 0, "Jun": 0, "Jul": 0, "Aug": 0, "Sep": 0, "Oct": 0, "Nov": 0, "Dec": 0, "Jan": 0, "Feb": 0, "Mar": 0}},
  {"itemCode": "3647580", "item1": "45 CF CHAIN PB14 SET", "area": "161", "plans": {"Apr": 0, "May": 0, "Jun": 0, "Jul": 0, "Aug": 0, "Sep": 0, "Oct": 0, "Nov": 0, "Dec": 0, "Jan": 0, "Feb": 0, "Mar": 0}},
  {"itemCode": "3588800", "item1": "03 CF CHAIN PB12 SET", "area": "161", "plans": {"Apr": 0, "May": 0, "Jun": 0, "Jul": 0, "Aug": 0, "Sep": 0, "Oct": 0, "Nov": 0, "Dec": 0, "Jan": 0, "Feb": 0, "Mar": 0}},
  {"itemCode": "3603620", "item1": "05 CI CHAIN PB16 SET", "area": "161", "plans": {"Apr": 0, "May": 0, "Jun": 0, "Jul": 0, "Aug": 0, "Sep": 0, "Oct": 0, "Nov": 0, "Dec": 0, "Jan": 0, "Feb": 0, "Mar": 0}},
  {"itemCode": "3684481", "item1": "05 M PB14 TAPE SET", "area": "161", "plans": {"Apr": 0, "May": 0, "Jun": 0, "Jul": 0, "Aug": 0, "Sep": 0, "Oct": 0, "Nov": 0, "Dec": 0, "Jan": 0, "Feb": 0, "Mar": 0}},
  {"itemCode": "3651561", "item1": "03 Y PB12 TAPE SET", "area": "161", "plans": {"Apr": 0, "May": 0, "Jun": 0, "Jul": 0, "Aug": 0, "Sep": 0, "Oct": 0, "Nov": 0, "Dec": 0, "Jan": 0, "Feb": 0, "Mar": 0}},
  {"itemCode": "8606970", "item1": "03 CFA CHAIN R12S1 SET", "area": "161", "plans": {"Apr": 0, "May": 0, "Jun": 0, "Jul": 0, "Aug": 0, "Sep": 0, "Oct": 0, "Nov": 0, "Dec": 0, "Jan": 0, "Feb": 0, "Mar": 0}},
  {"itemCode": "6394130", "item1": "03 CFBE CHAIN PB12 SET", "area": "161", "plans": {"Apr": 0, "May": 0, "Jun": 0, "Jul": 0, "Aug": 0, "Sep": 0, "Oct": 0, "Nov": 0, "Dec": 0, "Jan": 0, "Feb": 0, "Mar": 0}},
  {"itemCode": "8914991", "item1": "03 CF CHAIN PBB18 SET", "area": "161", "plans": {"Apr": 0, "May": 0, "Jun": 0, "Jul": 0, "Aug": 0, "Sep": 0, "Oct": 0, "Nov": 0, "Dec": 0, "Jan": 0, "Feb": 0, "Mar": 0}},
  {"itemCode": "6799451", "item1": "03 VS PB12 TAPE SET", "area": "161", "plans": {"Apr": 0, "May": 0, "Jun": 0, "Jul": 0, "Aug": 0, "Sep": 0, "Oct": 0, "Nov": 0, "Dec": 0, "Jan": 0, "Feb": 0, "Mar": 0}},
  {"itemCode": "3638191", "item1": "05 VS PB14 TAPE SET", "area": "161", "plans": {"Apr": 0, "May": 0, "Jun": 0, "Jul": 0, "Aug": 0, "Sep": 0, "Oct": 0, "Nov": 0, "Dec": 0, "Jan": 0, "Feb": 0, "Mar": 0}},
  {"itemCode": "3980200", "item1": "04 Y PB14 TAPE SET", "area": "161", "plans": {"Apr": 0, "May": 0, "Jun": 0, "Jul": 0, "Aug": 0, "Sep": 0, "Oct": 0, "Nov": 0, "Dec": 0, "Jan": 0, "Feb": 0, "Mar": 0}},
  {"itemCode": "8284061", "item1": "05 CIA CHAIN R16S1 SET", "area": "161", "plans": {"Apr": 0, "May": 0, "Jun": 0, "Jul": 0, "Aug": 0, "Sep": 0, "Oct": 0, "Nov": 0, "Dec": 0, "Jan": 0, "Feb": 0, "Mar": 0}},
  {"itemCode": "6394131", "item1": "05 CIBE CHAIN PB16 SET", "area": "161", "plans": {"Apr": 0, "May": 0, "Jun": 0, "Jul": 0, "Aug": 0, "Sep": 0, "Oct": 0, "Nov": 0, "Dec": 0, "Jan": 0, "Feb": 0, "Mar": 0}},
  {"itemCode": "3849070", "item1": "08 VS PB16 TAPE SET", "area": "161", "plans": {"Apr": 0, "May": 0, "Jun": 0, "Jul": 0, "Aug": 0, "Sep": 0, "Oct": 0, "Nov": 0, "Dec": 0, "Jan": 0, "Feb": 0, "Mar": 0}},
  {"itemCode": "6697960", "item1": "03 VS PBG12 TAPE SET", "area": "161", "plans": {"Apr": 0, "May": 0, "Jun": 0, "Jul": 0, "Aug": 0, "Sep": 0, "Oct": 0, "Nov": 0, "Dec": 0, "Jan": 0, "Feb": 0, "Mar": 0}},
  {"itemCode": "6697970", "item1": "05 VS PBG14 TAPE SET", "area": "161", "plans": {"Apr": 0, "May": 0, "Jun": 0, "Jul": 0, "Aug": 0, "Sep": 0, "Oct": 0, "Nov": 0, "Dec": 0, "Jan": 0, "Feb": 0, "Mar": 0}},
  {"itemCode": "8721451", "item1": "05 VS PBB18 TAPE SET", "area": "161", "plans": {"Apr": 0, "May": 0, "Jun": 0, "Jul": 0, "Aug": 0, "Sep": 0, "Oct": 0, "Nov": 0, "Dec": 0, "Jan": 0, "Feb": 0, "Mar": 0}},
  {"itemCode": "6657020", "item1": "03 Y R12S1 TAPE SET DOPE", "area": "161", "plans": {"Apr": 0, "May": 0, "Jun": 0, "Jul": 0, "Aug": 0, "Sep": 0, "Oct": 0, "Nov": 0, "Dec": 0, "Jan": 0, "Feb": 0, "Mar": 0}},
  {"itemCode": "8469230", "item1": "03 VS PBB18 TAPE SET", "area": "161", "plans": {"Apr": 0, "May": 0, "Jun": 0, "Jul": 0, "Aug": 0, "Sep": 0, "Oct": 0, "Nov": 0, "Dec": 0, "Jan": 0, "Feb": 0, "Mar": 0}},
  {"itemCode": "6393940", "item1": "POLYESTER ELEMENT EP050", "area": "312", "plans": {"Apr": 0, "May": 0, "Jun": 0, "Jul": 0, "Aug": 0, "Sep": 0, "Oct": 0, "Nov": 0, "Dec": 0, "Jan": 0, "Feb": 0, "Mar": 0}},
  {"itemCode": "208538", "item1": "POLYESTER ELEMENT EP050", "area": "312", "plans": {"Apr": 0, "May": 0, "Jun": 0, "Jul": 0, "Aug": 0, "Sep": 0, "Oct": 0, "Nov": 0, "Dec": 0, "Jan": 0, "Feb": 0, "Mar": 0}},
  {"itemCode": "3852200", "item1": "POLYESTER ELEMENT EP050 DOPE", "area": "312", "plans": {"Apr": 0, "May": 0, "Jun": 0, "Jul": 0, "Aug": 0, "Sep": 0, "Oct": 0, "Nov": 0, "Dec": 0, "Jan": 0, "Feb": 0, "Mar": 0}},
  {"itemCode": "1924600", "item1": "POLYESTER ELEMENT EP074", "area": "312", "plans": {"Apr": 0, "May": 0, "Jun": 0, "Jul": 0, "Aug": 0, "Sep": 0, "Oct": 0, "Nov": 0, "Dec": 0, "Jan": 0, "Feb": 0, "Mar": 0}},
  {"itemCode": "3850870", "item1": "POLYESTER ELEMENT EP074 DOPE", "area": "312", "plans": {"Apr": 0, "May": 0, "Jun": 0, "Jul": 0, "Aug": 0, "Sep": 0, "Oct": 0, "Nov": 0, "Dec": 0, "Jan": 0, "Feb": 0, "Mar": 0}},
  {"itemCode": "20109", "item1": "POLYESTER ELEMENT EP060", "area": "312", "plans": {"Apr": 0, "May": 0, "Jun": 0, "Jul": 0, "Aug": 0, "Sep": 0, "Oct": 0, "Nov": 0, "Dec": 0, "Jan": 0, "Feb": 0, "Mar": 0}},
  {"itemCode": "6095720", "item1": "POLYESTER ELEMENT EP074", "area": "312", "plans": {"Apr": 0, "May": 0, "Jun": 0, "Jul": 0, "Aug": 0, "Sep": 0, "Oct": 0, "Nov": 0, "Dec": 0, "Jan": 0, "Feb": 0, "Mar": 0}},
  {"itemCode": "3604270", "item1": "03 CF CHAIN PB12 NAT", "area": "313", "plans": {"Apr": 0, "May": 0, "Jun": 0, "Jul": 0, "Aug": 0, "Sep": 0, "Oct": 0, "Nov": 0, "Dec": 0, "Jan": 0, "Feb": 0, "Mar": 0}},
  {"itemCode": "3603611", "item1": "05 CI CHAIN PB16 NAT", "area": "313", "plans": {"Apr": 0, "May": 0, "Jun": 0, "Jul": 0, "Aug": 0, "Sep": 0, "Oct": 0, "Nov": 0, "Dec": 0, "Jan": 0, "Feb": 0, "Mar": 0}},
  {"itemCode": "8284062", "item1": "05 CIA CHAIN R16S1 NAT", "area": "313", "plans": {"Apr": 0, "May": 0, "Jun": 0, "Jul": 0, "Aug": 0, "Sep": 0, "Oct": 0, "Nov": 0, "Dec": 0, "Jan": 0, "Feb": 0, "Mar": 0}},
  {"itemCode": "6815520", "item1": "03 CFBE CHAIN PB12 NAT", "area": "313", "plans": {"Apr": 0, "May": 0, "Jun": 0, "Jul": 0, "Aug": 0, "Sep": 0, "Oct": 0, "Nov": 0, "Dec": 0, "Jan": 0, "Feb": 0, "Mar": 0}},
  {"itemCode": "8914992", "item1": "03 CF CHAIN PBB18 NAT", "area": "313", "plans": {"Apr": 0, "May": 0, "Jun": 0, "Jul": 0, "Aug": 0, "Sep": 0, "Oct": 0, "Nov": 0, "Dec": 0, "Jan": 0, "Feb": 0, "Mar": 0}},
  {"itemCode": "8284070", "item1": "03 CFA CHAIN R12S1 NAT", "area": "313", "plans": {"Apr": 0, "May": 0, "Jun": 0, "Jul": 0, "Aug": 0, "Sep": 0, "Oct": 0, "Nov": 0, "Dec": 0, "Jan": 0, "Feb": 0, "Mar": 0}},
  {"itemCode": "3647581", "item1": "45 CF CHAIN PB14 NAT", "area": "313", "plans": {"Apr": 0, "May": 0, "Jun": 0, "Jul": 0, "Aug": 0, "Sep": 0, "Oct": 0, "Nov": 0, "Dec": 0, "Jan": 0, "Feb": 0, "Mar": 0}},
  {"itemCode": "6814970", "item1": "05 CIBE CHAIN PB16 NAT", "area": "313", "plans": {"Apr": 0, "May": 0, "Jun": 0, "Jul": 0, "Aug": 0, "Sep": 0, "Oct": 0, "Nov": 0, "Dec": 0, "Jan": 0, "Feb": 0, "Mar": 0}}
]
